./.gitignore
./LICENSE
./MANIFEST.in
./PKG-INFO
./README.md
./loader.py
./pyproject.toml
./server.py
./update_schemas.py
./uv.lock
./version_manager.py
./schemas/groups.json
./schemas/version.json
./schemas/alert/categories.json
./schemas/alert/anomalous_behavior/abnormal_behavior_access_anomaly.json
./schemas/alert/anomalous_behavior/abnormal_behavior_host_abnormality.json
./schemas/alert/anomalous_behavior/abnormal_behavior_traffic_anomaly.json
./schemas/alert/data_security/data_security_data_leak.json
./schemas/alert/data_security/data_security_tampering.json
./schemas/alert/malware/malware_botnet.json
./schemas/alert/malware/malware_computer_virus.json
./schemas/alert/malware/malware_embedded_webpage.json
./schemas/alert/malware/malware_mining.json
./schemas/alert/malware/malware_network_worm.json
./schemas/alert/malware/malware_ransomware.json
./schemas/alert/malware/malware_trojan.json
./schemas/alert/network_attack/network_attack_backdoor_exploit.json
./schemas/alert/network_attack/network_attack_credential_attack.json
./schemas/alert/network_attack/network_attack_dos.json
./schemas/alert/network_attack/network_attack_email_threat.json
./schemas/alert/network_attack/network_attack_host_exploit.json
./schemas/alert/network_attack/network_attack_phishing.json
./schemas/alert/network_attack/network_attack_scan_probe.json
./schemas/alert/network_attack/network_attack_web.json
./schemas/alert/network_attack/network_attack_web_tampering.json
./schemas/alert/vulnerability_configuration_risk/vulnerability_configuration_database_risk.json
./schemas/alert/vulnerability_configuration_risk/vulnerability_configuration_host_risk.json
./schemas/alert/vulnerability_configuration_risk/vulnerability_configuration_weak_password.json
./schemas/alert/vulnerability_configuration_risk/vulnerability_configuration_website_risk.json
./schemas/asset/categories.json
./schemas/asset/business_asset/business_asset_app.json
./schemas/asset/business_asset/business_asset_mini_program.json
osim_test_mcp_server-1.0.3.dist-info/METADATA
osim_test_mcp_server-1.0.3.dist-info/WHEEL
osim_test_mcp_server-1.0.3.dist-info/entry_points.txt
osim_test_mcp_server-1.0.3.dist-info/licenses/LICENSE
osim_test_mcp_server-1.0.3.dist-info/RECORD
