Metadata-Version: 2.4
Name: osim-test-mcp-server
Version: 1.0.3
Summary: OSIM MCP Server based on FastMCP
Author-email: Delin <zdl0929@gmail.com>
License: Apache-2.0
License-File: LICENSE
Keywords: fastmcp,mcp,model-context-protocol,osim,security
Classifier: Development Status :: 4 - Beta
Classifier: Intended Audience :: Developers
Classifier: License :: OSI Approved :: Apache Software License
Classifier: Programming Language :: Python :: 3
Classifier: Programming Language :: Python :: 3.10
Classifier: Programming Language :: Python :: 3.11
Classifier: Programming Language :: Python :: 3.12
Requires-Python: >=3.10
Requires-Dist: aiohttp>=3.9.0
Requires-Dist: fastmcp>=2.0.0
